{"title":"","date":"2013-12-25T14:57:49.000Z","source":"_posts/no-title.md","raw":"date: 2013-12-25 22:57:49\ntags:\n---\n\nThis post doesn't have a title. Make sure it's accessible.","slug":"no-title","published":true,"updated":"2025-01-09T09:03:07.669Z","_id":"cm5p3pi2r000kl9ou4oddarei","comments":true,"layout":"post","photos":[],"html":"<p>This post doesn’t have a title. Make sure it’s accessible.</p>\n","excerpt":"","more":"<p>This post doesn’t have a title. Make sure it’s accessible.</p>\n","path":"2013/12/25/no-title/","permalink":"https://lhcfl.github.io/Anatolodemo/2013/12/25/no-title/","tags":[],"categories":[],"prev":{"title":"Images","date":"2013-12-26T14:46:49.000Z","slug":"images","published":true,"updated":"2025-01-09T09:03:07.669Z","_id":"cm5p3pi2o000gl9ou1vl9f9wt","layout":"post","photos":[],"excerpt":"","path":"2013/12/26/images/","permalink":"https://lhcfl.github.io/Anatolodemo/2013/12/26/images/","__post":true},"next":{"title":"Excerpts","date":"2013-12-24T16:23:23.000Z","slug":"excerpts","published":true,"updated":"2025-01-09T09:03:07.669Z","_id":"cm5p3pi2m000dl9ou04110u70","layout":"post","photos":[],"excerpt":"<p>The following contents should be invisible in home&#x2F;archive page.</p>","path":"2013/12/25/excerpts/","permalink":"https://lhcfl.github.io/Anatolodemo/2013/12/25/excerpts/","__post":true},"__post":true}